dekeyrej_secretmanager-1.1.5.dist-info/licenses/LICENSE
secretmanager/__init__.py
secretmanager/_crypto_utils.py
secretmanager/_k8s_ops.py
secretmanager/_kubevault_ops.py
secretmanager/_source_loader.py
secretmanager/_vault_ops.py
secretmanager/manager.py
secretmanager/secretregistry.py
secretmanager/verbregistry.py
dekeyrej_secretmanager-1.1.5.dist-info/METADATA
dekeyrej_secretmanager-1.1.5.dist-info/WHEEL
dekeyrej_secretmanager-1.1.5.dist-info/top_level.txt
dekeyrej_secretmanager-1.1.5.dist-info/RECORD
