Metadata-Version: 2.4
Name: dekeyrej-secretmanager
Version: 1.1.5
Summary: Modular secret management with Vault, Kubernetes, Environment and file backends.
Author-email: "Joseph S. DeKeyrel" <joedekeyrel@gmail.com>
License: MIT License
Classifier: License :: OSI Approved :: MIT License
Classifier: Programming Language :: Python
Classifier: Programming Language :: Python :: 3
Requires-Python: >=3.9
License-File: LICENSE
Requires-Dist: pyyaml
Requires-Dist: kubernetes
Requires-Dist: requests
Requires-Dist: hvac
Requires-Dist: python-dotenv
Dynamic: license-file
